tracemem/__init__.py
tracemem/tracemem.py
tracemem-0.5.0.dist-info/licenses/LICENSE
tracemem-0.5.0.dist-info/METADATA
tracemem-0.5.0.dist-info/WHEEL
tracemem-0.5.0.dist-info/top_level.txt
tracemem-0.5.0.dist-info/RECORD
