Metadata-Version: 2.4
Name: tracemem
Version: 0.5.0
Summary: A lightweight tool to measure and trace the full memory of a Python session
Author-email: Nyggus <nyggus@gmail.com>
License-Expression: MIT
Project-URL: Homepage, https://github.com/nyggus/tracemem/
Classifier: Intended Audience :: Developers
Classifier: Programming Language :: Python :: 3
Classifier: Programming Language :: Python :: 3.9
Classifier: Programming Language :: Python :: 3.10
Classifier: Programming Language :: Python :: 3.11
Classifier: Programming Language :: Python :: 3.12
Classifier: Programming Language :: Python :: 3.13
Classifier: Operating System :: OS Independent
Classifier: Topic :: Software Development :: Libraries :: Python Modules
Requires-Python: >=3.9
License-File: LICENSE
Requires-Dist: psutil
Requires-Dist: rounder
Provides-Extra: dev
Requires-Dist: wheel; extra == "dev"
Requires-Dist: black; extra == "dev"
Requires-Dist: pytest; extra == "dev"
Requires-Dist: mypy; extra == "dev"
Requires-Dist: setuptools; extra == "dev"
Requires-Dist: build; extra == "dev"
Dynamic: license-file
